hastur/__init__.py
hastur/arms.py
hastur/bandits.py
hastur/distributions.py
hastur/exceptions.py
hastur/observations.py
hastur-0.1.2.dist-info/DESCRIPTION.rst
hastur-0.1.2.dist-info/METADATA
hastur-0.1.2.dist-info/RECORD
hastur-0.1.2.dist-info/WHEEL
hastur-0.1.2.dist-info/metadata.json
hastur-0.1.2.dist-info/top_level.txt
